MANIFEST.in
README.md
setup.py
webbuild/__init__.py
webbuild/render.py
webbuild.egg-info/PKG-INFO
webbuild.egg-info/SOURCES.txt
webbuild.egg-info/dependency_links.txt
webbuild.egg-info/top_level.txt
webbuild.egg-info/zip-safe
webbuild/js/__init__.py
webbuild/js/script.py
webbuild/style/__init__.py
webbuild/style/attr.py
webbuild/style/style_class.py
webbuild/style/style_id.py
webbuild/style/style_sheet.py
webbuild/tag/__init__.py
webbuild/tag/abbr.py
webbuild/tag/address.py
webbuild/tag/anchor.py
webbuild/tag/area.py
webbuild/tag/article.py
webbuild/tag/aside.py
webbuild/tag/audio.py
webbuild/tag/b.py
webbuild/tag/base.py
webbuild/tag/bdi.py
webbuild/tag/bdo.py
webbuild/tag/big.py
webbuild/tag/blockquote.py
webbuild/tag/body.py
webbuild/tag/br.py
webbuild/tag/button.py
webbuild/tag/canvas.py
webbuild/tag/caption.py
webbuild/tag/center.py
webbuild/tag/cite.py
webbuild/tag/code.py
webbuild/tag/col.py
webbuild/tag/col_group.py
webbuild/tag/comment.py
webbuild/tag/data.py
webbuild/tag/datalist.py
webbuild/tag/dd.py
webbuild/tag/del_tag.py
webbuild/tag/details.py
webbuild/tag/dfn.py
webbuild/tag/dialog.py
webbuild/tag/div.py
webbuild/tag/dl.py
webbuild/tag/doc_type.py
webbuild/tag/dt.py
webbuild/tag/em.py
webbuild/tag/embed.py
webbuild/tag/fieldset.py
webbuild/tag/fig_caption.py
webbuild/tag/figure.py
webbuild/tag/footer.py
webbuild/tag/form.py
webbuild/tag/h.py
webbuild/tag/head.py
webbuild/tag/header.py
webbuild/tag/hr.py
webbuild/tag/html.py
webbuild/tag/html_tag.py
webbuild/tag/i.py
webbuild/tag/iframe.py
webbuild/tag/img.py
webbuild/tag/input.py
webbuild/tag/ins.py
webbuild/tag/kbd.py
webbuild/tag/label.py
webbuild/tag/legend.py
webbuild/tag/li.py
webbuild/tag/link.py
webbuild/tag/main.py
webbuild/tag/map.py
webbuild/tag/mark.py
webbuild/tag/meter.py
webbuild/tag/nav.py
webbuild/tag/no_script.py
webbuild/tag/object.py
webbuild/tag/ol.py
webbuild/tag/opt_group.py
webbuild/tag/option.py
webbuild/tag/output.py
webbuild/tag/p.py
webbuild/tag/param.py
webbuild/tag/picture.py
webbuild/tag/pre.py
webbuild/tag/progress.py
webbuild/tag/q.py
webbuild/tag/rp.py
webbuild/tag/rt.py
webbuild/tag/ruby.py
webbuild/tag/s.py
