Metadata-Version: 2.1
Name: webbuild
Version: 0.0.6
Summary: A library for making website
Home-page: https://github.com/Krprashant94
Author: Prashant Kumar
Author-email: kr.prashant94@gmail.com
Maintainer: WebBuild Developer Community
License: Testing Only
Platform: Windows
Platform: Linux
Platform: Solaris
Platform: Mac OS-X
Platform: Unix
Requires-Python: >=3.4
